MANIFEST.in
README.rst
setup.py
sometimes/__init__.py
sometimes/decorators.py
sometimes.egg-info/PKG-INFO
sometimes.egg-info/SOURCES.txt
sometimes.egg-info/dependency_links.txt
sometimes.egg-info/not-zip-safe
sometimes.egg-info/top_level.txt