Metadata-Version: 1.1
Name: sometimes
Version: 0.1.3
Summary: Stop being so black & white. Mix things up a bit and execute code sometimes.
Home-page: https://github.com/aaronbassett/sometimes
Author: Aaron Bassett
Author-email: aaron@rawtech.io
License: MIT
Keywords: sometimes
Platform: UNKNOWN
Classifier: Development Status :: 5 - Production/Stable
Classifier: Framework :: Django
Classifier: Intended Audience :: Developers
Classifier: License :: OSI Approved :: BSD License
Classifier: Natural Language :: English
Classifier: Programming Language :: Python :: 2
Classifier: Programming Language :: Python :: 2.7
Classifier: Programming Language :: Python :: 3
Classifier: Programming Language :: Python :: 3.4
